{
  "file": "technophobia_in_digital_health_contexts_review_2025.pdf",
  "pages": 18,
  "title_guess": "Technophobia in digital health contexts:",
  "abstract": "Abstract Objective: With the rapid integration of digital technologies into healthcare, technophobia has become a key barrier to digital health adoption, especially among older adults. This study aimed to evaluate technophobia levels and identify asso- ciated factors within a multidimensional ecological framework. Methods: A systematic search was conducted across 10 electronic databases for studies published until April 30, 2025. Meta-analysis was conducted to estimate pooled effect sizes. Technophobia levels were assessed using mean differences (MDs) or standardized mean differences (SMDs), each accompanied by a 95% con ﬁdence interval (CI). Summary correl- ation coef ﬁcients ( r), with 95% CI, were used to evaluate associated factors based on the health ecological model. Results: Nineteen studies were included. The ﬁndings indicate that older adults demonstrated signi ﬁcantly elevated technophobia levels (MD = 39.90, 95% CI: 35.87 –43.94) compared to non-older adults, with privacy and security con- cerns scoring the highest among the three dimensions (MD = 3.29, 95% CI: 2.94 –3.64). Additionally, several factors showed signiﬁcant correlations with technophobia ( r = −0.537 to 0.235, P < 0.05), spanning four ecological domains: indi- vidual traits (e.g. digital health literacy), behavioral traits (e.g. self-ef ﬁcacy), interpersonal networks (e.g. social networks), and living environment (e.g. income level). Conclusions: Technophobia is notably high among older adults in digital health contexts, especially regarding privacy and security concerns. Its roots span individual, social, and systemic dimensions. These ﬁndings highlight the need for targeted, multilevel interventions to reduce technophobia and ensure equitable access to digital health technologies. Keywords Technophobia, digital health, associated factors, meta-analysis, review Received: 14 May 2025; accepted: 14 August 2025",
  "conclusion": "Conclusion In digital health contexts, older adults exhibit elevated levels of technophobia, particularly concerning privacy and security. Using the health ecological model, we identi- ﬁed key correlates across four levels. At the individual level, low educational attainment, limited digital health lit- eracy, poor language pro ﬁciency, and high neuroticism — especially among older women —characterized a high-risk group. At the behavioral level, low self-ef ﬁcacy, limited technology use, and infrequent Internet use emerged as sig- niﬁcant risk factors. Within interpersonal networks, broader social connections exerted a protective effect, while family support showed only a marginal association. At the environ- mental level, income was weakly linked to technophobia. These ﬁndings underscore the importance of stratifying high-risk populations across ecological domains to better capture subgroup differences in technophobia and to inform precision-targeted interventions. Song et al. 15 Acknowledgments We thank the authors of the primary studies for their valuable contributions. ORCID iDs Xiaofang Song https:/ /orcid.org/0009-0000-4974-2177 Shasha Li https://orcid.org/0000-0003-4198-2314 Liying Dong https://orcid.org/0009-0009-5350-0205 Yue Li https://orcid.org/0009-0002-5274-9761 Xinyu Yang https://orcid.org/0009-0002-8340-9890 Jianyi Bao https://orcid.org/0009-0000-1139-7072 Shufang Liao https://orcid.org/0009-0001-8554-1556 Yingxue Xi https://orcid.org/0009-0003-5332-1510 Guojing Guo https://orcid.org/0009-0001-9069-1321 Contributorship Xiaofang Song: conceptualization, literature search, data extrac- tion, and writing —original draft. Shasha Li: supervision, method- ology, and writing—review and editing. Liying Dong and Yue Li: Data extraction and quality assessment. Xinyu Yang and Jianyi Bao: Formal analysis and interpretation of results. Shufang Liao, Yingxue Xi, and Guojing Guo: Manuscript editing and reference management. All authors read and approved the ﬁnal manuscript. Funding The authors disclosed receipt of the following ﬁnancial support for the research, authorship, and/or publication of this article: This work was supported by the National Outstanding Youth Science Fund Project of National Natural Science Foundation of China (grant number no. 72204084). Declaration of con ﬂicting interests The authors declared no potential con ﬂicts of interest with respect to the research, authorship, and/or publication of this article. Data availability statement All data used in this study are from publicly available sources. Supplemental material Supplemental material for this article is available online."
}